setup.py
thebot_instagram.py
thebot_instagram.egg-info/PKG-INFO
thebot_instagram.egg-info/SOURCES.txt
thebot_instagram.egg-info/dependency_links.txt
thebot_instagram.egg-info/requires.txt
thebot_instagram.egg-info/top_level.txt