Metadata-Version: 1.1
Name: thebot-instagram
Version: 0.1.1
Summary: Posts a new popular photo from the instagram each hour.
Home-page: http://github.com/svetlyak40wt/thebot-instagram/
Author: Alexander Artemenko
Author-email: svetlyak.40wt@gmail.com
License: New BSD License
Keywords: thebot instagram plugin
Platform: UNKNOWN
Classifier: Development Status :: 4 - Beta
Classifier: Environment :: Plugins
Classifier: Intended Audience :: Developers
Classifier: Intended Audience :: System Administrators
Classifier: License :: OSI Approved :: BSD License
Classifier: Programming Language :: Python
